setup.py
ArvadsFit/FitClass.py
ArvadsFit/__init__.py
ArvadsFit.egg-info/PKG-INFO
ArvadsFit.egg-info/SOURCES.txt
ArvadsFit.egg-info/dependency_links.txt
ArvadsFit.egg-info/not-zip-safe
ArvadsFit.egg-info/requires.txt
ArvadsFit.egg-info/top_level.txt