Metadata-Version: 1.0
Name: ArvadsFit
Version: 0.9
Summary: A custom wrapper of IMinuit
Home-page: https://github.com/Arvad/ArvadsFit
Author: Asbjorn Arvad Jorgensen
Author-email: Arvad91@gmail.com
License: MIT
Platform: UNKNOWN
